{
    "requireCurlyBraces": ["if", "else", "for", "while", "do", "try", "catch"],
    "requireSpaceAfterKeywords": ["if", "for", "while", "do", "switch", "try", "catch", "function", "return"],
    "requireSpacesInFunctionExpression": {
        "beforeOpeningCurlyBrace": true
    },
    "disallowKeywordsOnNewLine" : ["else"],
    "disallowMultipleLineBreaks" : true,
    "disallowLeftStickedOperators": ["?", "+", "/", "*", "=", "==", "===", "!=", "!==", ">", ">=", "<", "<="],
    "disallowRightStickedOperators": ["?", "+", "/", "*", ":", "=", "==", "===", "!=", "!==", ">", ">=", "<", "<="],
    "requireSpaceBeforeBinaryOperators": ["+", "-", "/", "*", "=", "==", "===", "!=", "!=="],
    "disallowSpaceAfterPrefixUnaryOperators": ["++", "--", "+", "-"],
    "disallowSpaceBeforePostfixUnaryOperators": ["++", "--"],
    "requireRightStickedOperators": ["!" ],
    "requireLeftStickedOperators": [","],
    "requireLineFeedAtFileEnd": true,
    "validateLineBreaks": "LF",
    "disallowSpaceAfterObjectKeys": true,
    "disallowKeywords": [ "with" ],
    "validateQuoteMarks": "'",
    "disallowMultipleVarDecl": true,
    "excludeFiles": [
        "node_modules",
        "tools",
        "test/fixtures"
    ]
}
